Workbook

Sheet All Errors
A1: Context | B1: Sentence | C1: Frequency | D1: Sample Index | E1: Dataset | F1: Dataset Type | G1: RAG | H1: Code | I1: Rationale | J1: Notes (4, 5, 7, 9)
A2: animal housing producing Dairy cattle, calf in China. Additional Context: The product of the assessment is Dairy cattle. | B2: ML model predicted No Dairy cattle, calf but the humans predicted Dairy cattle, calf. | C2: 0 | D2: 78 | E2: productQA | F2: original | G2: rag | H2: 1.1 | I2: =VLOOKUP(H2,'Encoding Errors'!$A$2:$B$16,2,FALSE) -> Label not in training data
A3: permanent pasture producing Hides, dairy cattle, fresh in United Kingdom. Additional description: based on a stocking density of two 650kg dairy cows per hectare and includes an allowance for followers. inventory is based on cows being housed for 250 days and outdoors for 115 days. Additional Context: The product being assessed is 1 L of packaged fluid milk. | B3: ML model predicted No Hides, dairy cattle, fresh but the humans predicted Hides, dairy cattle, fresh. | C3: 0 | D3: 79 | E3: productQA | F3: original | G3: rag | H3: 1.1 | I3: =VLOOKUP(H3,'Encoding Errors'!$A$2:$B$16,2,FALSE) -> Label not in training data
A4: permanent pasture producing Hides, dairy cattle, fresh in United Kingdom. Additional description: based on a stocking density of two 650kg dairy cows per hectare and includes an allowance for followers. inventory is based on cows being housed for 250 days and outdoors for 115 days. Additional Context: The product being assessed is 1 L of packaged fluid milk. | B4: ML model predicted No Hides but the humans predicted Hides. | C4: 0 | D4: 79 | E4: productQA | F4: original | G4: rag | H4: 1.1 | I4: =VLOOKUP(H4,'Encoding Errors'!$A$2:$B$16,2,FALSE) -> Label not in training data
A5: agri-food processor producing Caciotta in Southern Europe. Additional description: Processing and packaging cycle to transform milk into various dairy products.. Additional Context: The product being assessed is Caciotta, a type of Italian cheese. | B5: ML model predicted No Caciotta but the humans predicted Caciotta. | C5: 0 | D5: 82 | E5: productQA | F5: original | G5: rag | H5: 1.1 | I5: =VLOOKUP(H5,'Encoding Errors'!$A$2:$B$16,2,FALSE) -> Label not in training data
A6: agri-food processor producing Caciotta in Southern Europe. Additional description: Processing and packaging cycle to transform milk into various dairy products.. Additional Context: The product being assessed is Caciotta, a type of Italian cheese. | B6: ML model predicted No Caciotta but the humans predicted Caciotta. | C6: 0 | D6: 87 | E6: productQA | F6: original | G6: rag | H6: 1.1 | I6: =VLOOKUP(H6,'Encoding Errors'!$A$2:$B$16,2,FALSE) -> Label not in training data
A7: animal housing producing Electricity, produced on in site, solar PV. Additional description: Kipster-Laying hens scenario 1. Additional Context: The object of the assessment is the production of electricity from on-site solar PV and animal housing producing electricity, specifically Kipster-Laying hens scenario 1. | B7: ML model predicted No Electricity but the humans predicted Electricity. | C7: 0 | D7: 53 | E7: productQA | F7: recalculated | G7: rag | H7: 1.1 | I7: =VLOOKUP(H7,'Encoding Errors'!$A$2:$B$16,2,FALSE) -> Label not in training data
A8: animal housing producing Electricity, produced on in site, solar PV. Additional description: Kipster-Laying hens scenario 1. Additional Context: The object of the assessment is the production of electricity from on-site solar PV and animal housing producing electricity, specifically Kipster-Laying hens scenario 1. | B8: ML model predicted No Electricity, produced on but the humans predicted Electricity, produced on. | C8: 0 | D8: 53 | E8: productQA | F8: recalculated | G8: rag | H8: 1.1 | I8: =VLOOKUP(H8,'Encoding Errors'!$A$2:$B$16,2,FALSE) -> Label not in training data
A9: animal housing producing Electricity, produced on in site, solar PV. Additional description: Kipster-Laying hens scenario 3. Additional Context: The product of the assessment is eggs. | B9: ML model predicted No Electricity but the humans predicted Electricity. | C9: 0 | D9: 70 | E9: productQA | F9: recalculated | G9: rag | H9: 1.1 | I9: =VLOOKUP(H9,'Encoding Errors'!$A$2:$B$16,2,FALSE) -> Label not in training data
A10: animal housing producing Electricity, produced on in site, solar PV. Additional description: Kipster-Laying hens scenario 3. Additional Context: The product of the assessment is eggs. | B10: ML model predicted No Electricity, produced on but the humans predicted Electricity, produced on. | C10: 0 | D10: 70 | E10: productQA | F10: recalculated | G10: rag | H10: 1.1 | I10: =VLOOKUP(H10,'Encoding Errors'!$A$2:$B$16,2,FALSE) -> Label not in training data
A11: animal housing producing Dairy cattle, calf in China. | B11: ML model predicted No Dairy cattle, calf but the humans predicted Dairy cattle, calf. | C11: 0 | D11: 78 | E11: productQA | F11: original | G11: no rag | H11: 1.1 | I11: =VLOOKUP(H11,'Encoding Errors'!$A$2:$B$16,2,FALSE) -> Label not in training data
A12: permanent pasture producing Hides, dairy cattle, fresh in United Kingdom. Additional description: based on a stocking density of two 650kg dairy cows per hectare and includes an allowance for followers. inventory is based on cows being housed for 250 days and outdoors for 115 days. | B12: ML model predicted No Hides but the humans predicted Hides. | C12: 0 | D12: 79 | E12: productQA | F12: original | G12: no rag | H12: 1.1 | I12: =VLOOKUP(H12,'Encoding Errors'!$A$2:$B$16,2,FALSE) -> Label not in training data
A13: permanent pasture producing Hides, dairy cattle, fresh in United Kingdom. Additional description: based on a stocking density of two 650kg dairy cows per hectare and includes an allowance for followers. inventory is based on cows being housed for 250 days and outdoors for 115 days. | B13: ML model predicted No Hides, dairy cattle, fresh but the humans predicted Hides, dairy cattle, fresh. | C13: 0 | D13: 79 | E13: productQA | F13: original | G13: no rag | H13: 1.1 | I13: =VLOOKUP(H13,'Encoding Errors'!$A$2:$B$16,2,FALSE) -> Label not in training data
... A29: animal housing producing Dairy cattle, calf in China. | B29: ML model predicted Dairy cattle, cow but the humans predicted No Dairy cattle, cow. | C29: 1.686747 | D29: 78 | E29: productQA | F29: original | G29: no rag | H29: 1.2 | I29: =VLOOKUP(H29,'Encoding Errors'!$A$2:$B$16,2,FALSE) -> Label occurs <5% of the time in training samples
A30: animal housing producing Pig, sow in Denmark. Additional description: Sows. | B30: ML model predicted kg liveweight/head but the humans predicted No kg liveweight/head. | C30: 54.457831 | D30: 0 | E30: functionalUnitQA | F30: original | G30: no rag | H30: 8.1 | I30: =VLOOKUP(H30,'Encoding Errors'!$A$2:$B$16,2,FALSE) -> In FU, labeler only includes relative while AI model adds other categories | J30: Humans only labeled FU as "relative". An actual FU should have been chosen.
A31: permanent pasture producing Hides, dairy cattle, fresh in United Kingdom. Additional description: based on a stocking density of two 650kg dairy cows per hectare and includes an allowance for followers. inventory is based on cows being housed for 250 days and outdoors for 115 days. Additional Context: The product being assessed is 1 L of packaged fluid milk. | B31: ML model predicted Meat, dairy cattle (liveweight) but the humans predicted No Meat, dairy cattle (liveweight). | C31: 2.6506024 | D31: 79 | E31: productQA | F31: original | G31: rag | H31: 1.2 | I31: =VLOOKUP(H31,'Encoding Errors'!$A$2:$B$16,2,FALSE) -> Label occurs <5% of the time in training samples
A32: permanent pasture producing Hides, dairy cattle, fresh in United Kingdom. Additional description: based on a stocking density of two 650kg dairy cows per hectare and includes an allowance for followers. inventory is based on cows being housed for 250 days and outdoors for 115 days. | B32: ML model predicted Meat, dairy cattle (liveweight) but the humans predicted No Meat, dairy cattle (liveweight). | C32: 2.6506024 | D32: 79 | E32: productQA | F32: original | G32: no rag | H32: 1.2 | I32: =VLOOKUP(H32,'Encoding Errors'!$A$2:$B$16,2,FALSE) -> Label occurs <5% of the time in training samples
A33: animal housing producing Milk, cow, raw (FPCM) in Italy. Additional description: Permanent Meadows Farm - representative of farms located in the Po plain where the cattle were fed principally with forage, compound feed and small quantities of alfalfa and corn feed, without silage feed and protein ingredients. In this system, the forage has spontaneously grown solely in the grassland of the farm and, during warmer seasons, has been left to dry into hay. Therefore, the milk produced is commonly known as â€œhay milkâ€, destined to produce Grana Padano cheese as well. Differentiating from the other plain systems, in PMF, meadows were never alternated with other crops, and there was no ploughing or harrowing, only mowing and irrigation. The cattle had the possibility to go in the outdoor paddock during the summer season.. Additional Context: For the given production system, the appropriate allocation method is:System expansion is not necessary, as the system is already representative of a specific agricultural production system (permanent meadows farm). Therefore, the answer is: "none required". | B33: ML model predicted No biophysical but the humans predicted biophysical. | C33: 3.1325301 | D33: 46 | E33: allocationQA | F33: original | G33: rag | H33: 1.2 | I33: =VLOOKUP(H33,'Encoding Errors'!$A$2:$B$16,2,FALSE) -> Label occurs <5% of the time in training samples
A34: permanent pasture producing Hides, dairy cattle, fresh in United Kingdom. Additional description: based on a stocking density of two 650kg dairy cows per hectare and includes an allowance for followers. inventory is based on cows being housed for 250 days and outdoors for 115 days. Additional Context: The product being assessed is 1 L of packaged fluid milk. | B34: ML model predicted Dairy cattle but the humans predicted No Dairy cattle. | C34: 3.1325301 | D34: 79 | E34: productQA | F34: original | G34: rag | H34: 1.2 | I34: =VLOOKUP(H34,'Encoding Errors'!$A$2:$B$16,2,FALSE) -> Label occurs <5% of the time in training samples
A35: animal housing producing Milk, cow, raw (FPCM) in Italy. Additional description: Permanent Meadows Farm - representative of farms located in the Po plain where the cattle were fed principally with forage, compound feed and small quantities of alfalfa and corn feed, without silage feed and protein ingredients. In this system, the forage has spontaneously grown solely in the grassland of the farm and, during warmer seasons, has been left to dry into hay. Therefore, the milk produced is commonly known as â€œhay milkâ€, destined to produce Grana Padano cheese as well. Differentiating from the other plain systems, in PMF, meadows were never alternated with other crops, and there was no ploughing or harrowing, only mowing and irrigation. The cattle had the possibility to go in the outdoor paddock during the summer season.. | B35: ML model predicted No biophysical but the humans predicted biophysical. | C35: 3.1325301 | D35: 46 | E35: allocationQA | F35: original | G35: no rag | H35: 1.2 | I35: =VLOOKUP(H35,'Encoding Errors'!$A$2:$B$16,2,FALSE) -> Label occurs <5% of the time in training samples
A36: producing Broiler chicken in Russia. Additional description: Poultry production under the conditions of the central region in european Russia. Additional Context: For the production system of producing Broiler chicken in Russia, the appropriate allocation method is "none required" because system expansion is not necessary. This is because the production system is relatively simple and does not involve complex co-products that require allocation. | B36: ML model predicted biophysical but the humans predicted No biophysical. | C36: 3.1325301 | D36: 68 | E36: allocationQA | F36: original | G36: rag | H36: 1.2 | I36: =VLOOKUP(H36,'Encoding Errors'!$A$2:$B$16,2,FALSE) -> Label occurs <5% of the time in training samples
A37: permanent pasture producing Milk, cow, raw (FPCM) in Ireland. Additional description: A representative sample of Irish dairy farms.. | B37: ML model predicted No biophysical but the humans predicted biophysical. | C37: 3.1325301 | D37: 73 | E37: allocationQA | F37: original | G37: no rag | H37: 1.2 | I37: =VLOOKUP(H37,'Encoding Errors'!$A$2:$B$16,2,FALSE) -> Label occurs <5% of the time in training samples
A38: permanent pasture producing Hides, dairy cattle, fresh in United Kingdom. Additional description: based on a stocking density of two 650kg dairy cows per hectare and includes an allowance for followers. inventory is based on cows being housed for 250 days and outdoors for 115 days. | B38: ML model predicted Dairy cattle but the humans predicted No Dairy cattle. | C38: 3.1325301 | D38: 79 | E38: productQA | F38: original | G38: no rag | H38: 1.2 | I38: =VLOOKUP(H38,'Encoding Errors'!$A$2:$B$16,2,FALSE) -> Label occurs <5% of the time in training samples
A39: permanent pasture producing Milk, cow, raw (FPCM) in Ireland. Additional description: A representative sample of Irish dairy farms.. Additional Context: Based on the provided information, the appropriate allocation method for the permanent pasture producing Milk, cow, raw (FPCM) in Ireland is:System expansion is not necessary in this case, as the production system is a simple, single-product system. Therefore, the answer is: "none required". | B39: ML model predicted No biophysical but the humans predicted biophysical. | C39: 3.1325301 | D39: 73 | E39: allocationQA | F39: original | G39: rag | H39: 1.2 | I39: =VLOOKUP(H39,'Encoding Errors'!$A$2:$B$16,2,FALSE) -> Label occurs <5% of the time in training samples
A40: animal housing producing Pig, sow in Denmark. Additional description: Sows. Additional Context: The functional unit for the production system "animal housing producing Pig, sow in Denmark" is 1 kg of live weight (LW) of pigs leaving the pig unit, including culled SOWS and slaughter pigs. | B40: ML model predicted kg liveweight/head but the humans predicted No kg liveweight/head. | C40: 54.457831 | D40: 0 | E40: functionalUnitQA | F40: original | G40: rag | H40: 8.1 | I40: =VLOOKUP(H40,'Encoding Errors'!$A$2:$B$16,2,FALSE) -> In FU, labeler only includes relative while AI model adds other categories | J40: Human labelers did not give a specific FU besides "relative", which is a binary with ha.
A41: permanent pasture producing Sheep, ewe in United Kingdom. Additional description: High sugar pasture for sheep and cattle.. Additional Context: The functional unit for the production system of permanent pasture producing sheep in the United Kingdom is 1 ewe. | B41: ML model predicted No kg cold carcass weight/head but the humans predicted kg cold carcass weight/head. | C41: 16.86747 | D41: 17 | E41: functionalUnitQA | F41: original | G41: rag | H41: 8.2 | I41: =VLOOKUP(H41,'Encoding Errors'!$A$2:$B$16,2,FALSE) -> In FU, AI model confuses cold carcass weight, cold dressed carcass weight, and liveweight | J41: Confused cold carcass weight with live weight
A42: permanent pasture producing Sheep, ewe in United Kingdom. Additional description: High sugar pasture for sheep and cattle.. | B42: ML model predicted No kg cold carcass weight/head but the humans predicted kg cold carcass weight/head. | C42: 16.86747 | D42: 17 | E42: functionalUnitQA | F42: original | G42: no rag | H42: 8.2 | I42: =VLOOKUP(H42,'Encoding Errors'!$A$2:$B$16,2,FALSE) -> In FU, AI model confuses cold carcass weight, cold dressed carcass weight, and liveweight | J42: Discrepancy between cold carcass weight/head and liveweight/head
A43: permanent pasture producing Beef cattle, cow in Brazil. Additional description: Beef, fertilized Guinea grass (Panicum maximum cv. TanzÃ¢nia) pasture + 75-day finishing period in confinement (Scenario 5). | B43: ML model predicted relative but the humans predicted No relative. | C43: 95.301205 | D43: 23 | E43: functionalUnitQA | F43: original | G43: no rag | H43: 1.4 | I43: =VLOOKUP(H43,'Encoding Errors'!$A$2:$B$16,2,FALSE) -> Label occurs >90% of the time in training samples
A44: agri-food processor producing Ripened cheese in Italy. Additional description: Grana Padano cheese production. What is in the system boundary? Additional Context: The system boundary of the Parmigiano-Reggiano production system includes:1. Dairy farm (Subsystem 1: Concentrated feed production, Subsystem 2: Fodder production, and Subsystem 3: Milk production)2. Raw milk transport3. Cheese making4. Product transport5. Product transport6. Product and by-products7. Emissions to Air, Water, and SoilThe system excludes:1. Land use and soil quality changes2. Production of raw milk components (rennet, starter culture, calcium chloride, and saltpetre)3. Delivery of final products to wholesale and retailers4. Consumption phase of the different products | B44: ML model predicted True_transport but the humans predicted No True_transport. | C44: 4.9681529 | D44: 15 | E44: systemBoundaryQA | F44: recalculated | G44: rag | H44: 1.2 | I44: =VLOOKUP(H44,'Encoding Errors'!$A$2:$B$16,2,FALSE) -> Label occurs <5% of the time in training samples
A45: agri-food processor producing Ripened cheese in Italy. Additional description: Grana Padano cheese production. What is in the system boundary? Additional Context: The system boundary of the Parmigiano-Reggiano production system includes:1. Dairy farm (Subsystem 1: Concentrated feed production, Subsystem 2: Fodder production, and Subsystem 3: Milk production)2. Raw milk transport3. Cheese making4. Product transport5. Product transport6. Product and by-products7. Emissions to Air, Water, and SoilThe system excludes:1. Land use and soil quality changes2. Production of raw milk components (rennet, starter culture, calcium chloride, and saltpetre)3. Delivery of final products to wholesale and retailers4. Consumption phase of the different products | B45: ML model predicted True_transport but the humans predicted No True_transport. | C45: 4.9681529 | D45: 20 | E45: systemBoundaryQA | F45: recalculated | G45: rag | H45: 1.2 | I45: =VLOOKUP(H45,'Encoding Errors'!$A$2:$B$16,2,FALSE) -> Label occurs <5% of the time in training samples
A46: agri-food processor producing Ripened cheese in Italy. Additional description: Grana Padano cheese production. What is in the system boundary? | B46: ML model predicted True_transport but the humans predicted No True_transport. | C46: 4.9681529 | D46: 15 | E46: systemBoundaryQA | F46: recalculated | G46: no rag | H46: 1.2 | I46: =VLOOKUP(H46,'Encoding Errors'!$A$2:$B$16,2,FALSE) -> Label occurs <5% of the time in training samples
A47: agri-food processor producing Ripened cheese in Italy. Additional description: Grana Padano cheese production. What is in the system boundary? | B47: ML model predicted True_transport but the humans predicted No True_transport. | C47: 4.9681529 | D47: 20 | E47: systemBoundaryQA | F47: recalculated | G47: no rag | H47: 1.2 | I47: =VLOOKUP(H47,'Encoding Errors'!$A$2:$B$16,2,FALSE) -> Label occurs <5% of the time in training samples
A48: permanent pasture producing Beef cattle in Brazil. Additional description: Rerfence system where feeding is performed only by grazing anfd the supply of mineral supplementation.. What is in the system boundary? | B48: ML model predicted No True_transport but the humans predicted True_transport. | C48: 5.4216867 | D48: 48 | E48: systemBoundaryQA | F48: original | G48: no rag | H48: 1.3 | I48: =VLOOKUP(H48,'Encoding Errors'!$A$2:$B$16,2,FALSE) -> Label occurs <10% of the time in training samples
A49: agri-food processor producing Meat, beef cattle (cold carcass weight) in Brazil. Additional description: Meat, beef (carcass-weight) - Mate Grosso country (Acroizal, Agua Boa, Brasnorte, Canarana, Chapada dos Guimaraes, Colider, Cuiaba, Gaucha do Norte, Nobres, Pedra Preta, Rondonopolis). What is in the system boundary? Additional Context: Here is a summary of the system boundary relevant to the context:* For beef production systems: + System boundary: "cradle to farm-gate" perspective + Includes: - Farming systems (EXT and INT) - Grazing and feeding systems - Breeding and reproduction- Manure management - Energy use (diesel fuel and electricity) - Nutrient balances (fertilizers, manure, etc.) + Excludes: - Upstream cutoff systems (e.g. construction, equipment maintenance, services)- Downstream processes (e.g. processing, packaging, distribution)* For agri-food processor producing meat: + System boundary: includes production of meat, beef cattle (cold carcass weight) + Includes: - Farming systems (EXT and INT) - Grazing and feeding systems - Breeding and reproduction - Manure management - Energy use (diesel fuel and electricity) - Nutrient balances (fertilizers, manure, etc.) + Excludes: - Upstream processes (e.g. feed production, processing, packaging) | B49: ML model predicted True_transport but the humans predicted No True_transport. | C49: 5.4216867 | D49: 53 | E49: systemBoundaryQA | F49: original | G49: rag | H49: 1.3 | I49: =VLOOKUP(H49,'Encoding Errors'!$A$2:$B$16,2,FALSE) -> Label occurs <10% of the time in training samples
A50: permanent pasture producing Milk, cow, raw in United Kingdom. Additional description: based on a stocking density of two 650kg dairy cows per hectare and includes an allowance for followers. inventory is based on cows being housed for 250 days and outdoors for 115 days. What is in the system boundary? Additional Context: The system boundary of the production system includes:* Dairy herd (lactating and dry cows, heifers, calves, and bulls)* Feed production (organic alfalfa, silages, grain premix, and other grass hays and silages)* Irrigation, fertilizers, pesticides, and machinery* Non-local feeds with related production and transport processes* Ancillary inputs (fuels, electricity, and drinking water for the cattle)* Farm buildings, roads, and tools* Equipment for grazing and haying* Manure and waste management* Pasture management (irrigation, manure spreading, and seeding)* Diffuse emissions (N2O, CH4) from manure spread or deposited on pastures* Milk processing plant (ultrapasteurization, homogenization, and packaging)* Transportation of animal feed and milk products* Employee transport and corporate office operation* Farming and grazing activities (including pasture management and animal husbandry)* Manure and waste treatment* Packaging and storage of milk and dairy products* Emissions to soil, water, and air from the entire production process. | B50: ML model predicted No True_transport but the humans predicted True_transport. | C50: 5.4216867 | D50: 54 | E50: systemBoundaryQA | F50: original | G50: rag | H50: 1.3 | I50: =VLOOKUP(H50,'Encoding Errors'!$A$2:$B$16,2,FALSE) -> Label occurs <10% of the time in training samples
A51: permanent pasture producing Hides, dairy cattle, fresh in United Kingdom. Additional description: based on a stocking density of two 650kg dairy cows per hectare and includes an allowance for followers. inventory is based on cows being housed for 250 days and outdoors for 115 days. What is in the system boundary? Additional Context: The system boundary of the production system includes:- Dairy cattle (lactating and dry cows, heifers, calves, and bulls)- Non-lactating animals (bulls for insemination and labor, female calves and heifers for replacement, male calves and young bulls for sale)- Feed production (fertilizers, pesticides, machinery, non-local feeds, and local feeds)- Irrigation, manure spreading, and seeding of pastures- Drinking water for cattle- Equipment (roads, irrigation infrastructure, buildings, and tools)- Ancillary inputs (fuels and electricity)- Carbon sequestration and biogenic carbon emissions of locally produced feeds (not considered due to vegetation cycles shorter than one year)- Pasture production (for grazing systems)- Crop production (for mixed farming systems)- Manure- Feed- Animal transport- Grazing systems (for grazing systems)- Mixed farming systems (communal grazing, crop residues, and crops)- Industrial systems (poultry production, pig production, ruminant feedlot meat production, and large-scale dairy production)- Manure (exported from AOD farms)- Feed supplier farms- Consolidators (for non-local feeds)- Pasture acreages | B51: ML model predicted No True_transport but the humans predicted True_transport. | C51: 5.4216867 | D51: 79 | E51: systemBoundaryQA | F51: original | G51: rag | H51: 1.3 | I51: =VLOOKUP(H51,'Encoding Errors'!$A$2:$B$16,2,FALSE) -> Label occurs <10% of the time in training samples
A52: permanent pasture producing Milk, cow, raw in United Kingdom. Additional description: based on a stocking density of two 650kg dairy cows per hectare and includes an allowance for followers. inventory is based on cows being housed for 250 days and outdoors for 115 days. What is in the system boundary? | B52: ML model predicted No True_transport but the humans predicted True_transport. | C52: 5.4216867 | D52: 54 | E52: systemBoundaryQA | F52: original | G52: no rag | H52: 1.3 | I52: =VLOOKUP(H52,'Encoding Errors'!$A$2:$B$16,2,FALSE) -> Label occurs <10% of the time in training samples
A53: permanent pasture producing Hides, dairy cattle, fresh in United Kingdom. Additional description: based on a stocking density of two 650kg dairy cows per hectare and includes an allowance for followers. inventory is based on cows being housed for 250 days and outdoors for 115 days. What is in the system boundary? | B53: ML model predicted No True_transport but the humans predicted True_transport. | C53: 5.4216867 | D53: 79 | E53: systemBoundaryQA | F53: original | G53: no rag | H53: 1.3 | I53: =VLOOKUP(H53,'Encoding Errors'!$A$2:$B$16,2,FALSE) -> Label occurs <10% of the time in training samples
A54: animal housing producing Electricity, produced on in site, solar PV. Additional description: Kipster-Laying hens scenario 1. Additional Context: The object of the assessment is the production of electricity from on-site solar PV and animal housing producing electricity, specifically Kipster-Laying hens scenario 1. | B54: ML model predicted Layer chicken but the humans predicted No Layer chicken. | C54: 6.6242038 | D54: 53 | E54: productQA | F54: recalculated | G54: rag | H54: 1.3 | I54: =VLOOKUP(H54,'Encoding Errors'!$A$2:$B$16,2,FALSE) -> Label occurs <10% of the time in training samples
... A75: permanent pasture producing Beef cattle, cow in Brazil. Additional description: Beef, fertilized Guinea grass (Panicum maximum cv. TanzÃ¢nia) pasture + 75-day finishing period in confinement (Scenario 5). Additional Context: The functional unit for the beef production system is 1 kg of live weight (LW) of beef cattle. | B75: ML model predicted relative but the humans predicted No relative. | C75: 95.301205 | D75: 23 | E75: functionalUnitQA | F75: original | G75: rag | H75: 1.4 | I75: =VLOOKUP(H75,'Encoding Errors'!$A$2:$B$16,2,FALSE) -> Label occurs >90% of the time in training samples
A76: animal housing producing Beef cattle, calf (male, weaned) in United Kingdom. Additional description: Indoor cattle system.. Additional Context: The functional unit for the animal housing producing Beef cattle, calf (male, weaned) in the United Kingdom is 1 kg of live weight (LW) of beef cattle. | B76: ML model predicted kg liveweight/head but the humans predicted No kg liveweight/head. | C76: 54.457831 | D76: 25 | E76: functionalUnitQA | F76: original | G76: rag | H76: 8.1 | I76: =VLOOKUP(H76,'Encoding Errors'!$A$2:$B$16,2,FALSE) -> In FU, labeler only includes relative while AI model adds other categories | J76: Only included "relative" as a FU, which is less specific
A77: permanent pasture producing Sheep, ewe in United Kingdom. Additional description: High sugar pasture for sheep and cattle.. Additional Context: The functional unit for the production system of permanent pasture producing sheep in the United Kingdom is 1 ewe. | B77: ML model predicted No kg cold carcass weight/head but the humans predicted kg cold carcass weight/head. | C77: 16.86747 | D77: 33 | E77: functionalUnitQA | F77: original | G77: rag | H77: 8.2 | I77: =VLOOKUP(H77,'Encoding Errors'!$A$2:$B$16,2,FALSE) -> In FU, AI model confuses cold carcass weight, cold dressed carcass weight, and liveweight | J77: Confused cold carcass weight with live weight
A78: animal housing producing Layer chicken, pullet in Mexico. Additional description: Chick breeding (6 weeks). Additional Context: The functional unit for the production system of animal housing producing Layer chicken, pullet in Mexico is a kilogram of egg production. | B78: ML model predicted kg liveweight/head but the humans predicted No kg liveweight/head. | C78: 54.457831 | D78: 41 | E78: functionalUnitQA | F78: original | G78: rag | H78: 8.1 | I78: =VLOOKUP(H78,'Encoding Errors'!$A$2:$B$16,2,FALSE) -> In FU, labeler only includes relative while AI model adds other categories
A79: permanent pasture producing Milk, cow, raw in United Kingdom. Additional description: based on a stocking density of two 650kg dairy cows per hectare and includes an allowance for followers. inventory is based on cows being housed for 250 days and outdoors for 115 days. Additional Context: The functional unit for the production system is 1 kg of raw milk from permanent pasture. | B79: ML model predicted No 1 ha but the humans predicted 1 ha. | C79: 4.6987952 | D79: 54 | E79: functionalUnitQA | F79: original | G79: rag | H79: 1.2 | I79: =VLOOKUP(H79,'Encoding Errors'!$A$2:$B$16,2,FALSE) -> Label occurs <5% of the time in training samples
A80: animal housing producing Dairy cattle, cow in Southern Europe. Additional description: Aggregate cycle representing all 75 dairy farms sampled. | B80: ML model predicted kg liveweight/head but the humans predicted No kg liveweight/head. | C80: 54.457831 | D80: 31 | E80: functionalUnitQA | F80: original | G80: no rag | H80: 8.1 | I80: =VLOOKUP(H80,'Encoding Errors'!$A$2:$B$16,2,FALSE) -> In FU, labeler only includes relative while AI model adds other categories
A81: permanent pasture producing Sheep, ewe in United Kingdom. Additional description: High sugar pasture for sheep and cattle.. | B81: ML model predicted No kg cold carcass weight/head but the humans predicted kg cold carcass weight/head. | C81: 16.86747 | D81: 33 | E81: functionalUnitQA | F81: original | G81: no rag | H81: 8.2 | I81: =VLOOKUP(H81,'Encoding Errors'!$A$2:$B$16,2,FALSE) -> In FU, AI model confuses cold carcass weight, cold dressed carcass weight, and liveweight
A82: animal housing producing Layer chicken, pullet in Mexico. Additional description: Chick breeding (6 weeks). | B82: ML model predicted days but the humans predicted No days. | C82: 10 | D82: 41 | E82: functionalUnitQA | F82: original | G82: no rag | H82: 4 | I82: =VLOOKUP(H82,'Encoding Errors'!$A$2:$B$16,2,FALSE) -> AI model likely incorrect
A83: permanent pasture producing Sheep, ewe in United Kingdom. Additional description: Generic grass pasture for sheep and cattle.. Additional Context: The functional unit for the production system of permanent pasture producing sheep in the United Kingdom is one sheep. | B83: ML model predicted kg cold carcass weight/head but the humans predicted No kg cold carcass weight/head. | C83: 18.216561 | D83: 5 | E83: functionalUnitQA | F83: recalculated | G83: rag | H83: 8.2 | I83: =VLOOKUP(H83,'Encoding Errors'!$A$2:$B$16,2,FALSE) -> In FU, AI model confuses cold carcass weight, cold dressed carcass weight, and liveweight
A84: animal housing producing Sheep, ram in United Kingdom. Additional description: Indoor cattle system.. Additional Context: The functional unit for the animal housing producing Sheep, ram in United Kingdom is not explicitly stated. However, based on the context, it can be inferred that the functional unit is likely to be 1 kg of live weight (LW) of sheep, as this is a common functional unit used in agricultural life cycle assessments (LCAs) for livestock production systems. | B84: ML model predicted kg cold carcass weight/head but the humans predicted No kg cold carcass weight/head. | C84: 18.216561 | D84: 10 | E84: functionalUnitQA | F84: recalculated | G84: rag | H84: 8.1 | I84: =VLOOKUP(H84,'Encoding Errors'!$A$2:$B$16,2,FALSE) -> In FU, labeler only includes relative while AI model adds other categories
A85: animal housing producing Sheep, ram in United Kingdom. Additional description: Indoor cattle system.. Additional Context: The functional unit for the animal housing producing Sheep, ram in United Kingdom is not explicitly stated. However, based on the context, it can be inferred that the functional unit is likely to be 1 kg of live weight (LW) of sheep, as this is a common functional unit used in agricultural life cycle assessments (LCAs) for livestock production systems. | B85: ML model predicted kg liveweight/head but the humans predicted No kg liveweight/head. | C85: 56.815287 | D85: 10 | E85: functionalUnitQA | F85: recalculated | G85: rag | H85: 8.1 | I85: =VLOOKUP(H85,'Encoding Errors'!$A$2:$B$16,2,FALSE) -> In FU, labeler only includes relative while AI model adds other categories
A86: permanent pasture producing Sheep, ewe in United Kingdom. Additional description: Generic grass pasture for sheep and cattle.. Additional Context: The functional unit for the production system of permanent pasture producing sheep in the United Kingdom is one animal. | B86: ML model predicted kg cold carcass weight/head but the humans predicted No kg cold carcass weight/head. | C86: 18.216561 | D86: 11 | E86: functionalUnitQA | F86: recalculated | G86: rag | H86: 8.2 | I86: =VLOOKUP(H86,'Encoding Errors'!$A$2:$B$16,2,FALSE) -> In FU, AI model confuses cold carcass weight, cold dressed carcass weight, and liveweight
A87: permanent pasture producing Sheep, ewe in United Kingdom. Additional description: Generic grass pasture for sheep and cattle.. | B87: ML model predicted kg liveweight/head but the humans predicted No kg liveweight/head. | C87: 56.815287 | D87: 18 | E87: functionalUnitQA | F87: recalculated | G87: no rag | H87: 8.1 | I87: =VLOOKUP(H87,'Encoding Errors'!$A$2:$B$16,2,FALSE) -> In FU, labeler only includes relative while AI model adds other categories | J87: Fairly unclear why unitless is ever considered a functional unit
A88: permanent pasture producing Sheep, ewe in United Kingdom. Additional description: Generic grass pasture for sheep and cattle.. Additional Context: The functional unit for the production system of permanent pasture producing sheep in the United Kingdom is one animal. | B88: ML model predicted kg cold carcass weight/head but the humans predicted No kg cold carcass weight/head. | C88: 18.216561 | D88: 18 | E88: functionalUnitQA | F88: recalculated | G88: rag | H88: 8.1 | I88: =VLOOKUP(H88,'Encoding Errors'!$A$2:$B$16,2,FALSE) -> In FU, labeler only includes relative while AI model adds other categories
A89: permanent pasture producing Sheep, ewe in United Kingdom. Additional description: Generic grass pasture for sheep and cattle.. Additional Context: The functional unit for the production system of permanent pasture producing sheep in the United Kingdom is one animal. | B89: ML model predicted kg liveweight/head but the humans predicted No kg liveweight/head. | C89: 56.815287 | D89: 18 | E89: functionalUnitQA | F89: recalculated | G89: rag | H89: 8.1 | I89: =VLOOKUP(H89,'Encoding Errors'!$A$2:$B$16,2,FALSE) -> In FU, labeler only includes relative while AI model adds other categories
A90: animal housing producing Beef cattle, calf (female, weaned) in United Kingdom. Additional description: Indoor cattle system.. | B90: ML model predicted kg liveweight/head but the humans predicted No kg liveweight/head. | C90: 56.815287 | D90: 31 | E90: functionalUnitQA | F90: recalculated | G90: no rag | H90: 8.1 | I90: =VLOOKUP(H90,'Encoding Errors'!$A$2:$B$16,2,FALSE) -> In FU, labeler only includes relative while AI model adds other categories
A91: animal housing producing Layer chicken, pullet in Mexico. Additional description: Chick breeding (6 weeks). | B91: ML model predicted kg liveweight/head but the humans predicted No kg liveweight/head. | C91: 54.457831 | D91: 41 | E91: functionalUnitQA | F91: original | G91: no rag | H91: 8.1 | I91: =VLOOKUP(H91,'Encoding Errors'!$A$2:$B$16,2,FALSE) -> In FU, labeler only includes relative while AI model adds other categories
A92: permanent pasture producing Milk, cow, raw in United Kingdom. Additional description: based on a stocking density of two 650kg dairy cows per hectare and includes an allowance for followers. inventory is based on cows being housed for 250 days and outdoors for 115 days. Additional Context: The functional unit for the production system is 1 kg of raw milk from permanent pasture. | B92: ML model predicted % but the humans predicted No %. | C92: 11.084337 | D92: 54 | E92: functionalUnitQA | F92: original | G92: rag | H92: 5 | I92: =VLOOKUP(H92,'Encoding Errors'!$A$2:$B$16,2,FALSE) -> AI model has justifiable response | J92: Milk processes are commonly encoded as % in Hestia, but not always.
A93: permanent pasture producing Milk, cow, raw in United Kingdom. Additional description: based on a stocking density of two 650kg dairy cows per hectare and includes an allowance for followers. inventory is based on cows being housed for 250 days and outdoors for 115 days. Additional Context: The functional unit for the production system is 1 kg of raw milk from permanent pasture. | B93: ML model predicted relative but the humans predicted No relative. | C93: 95.301205 | D93: 54 | E93: functionalUnitQA | F93: original | G93: rag | H93: 1.4 | I93: =VLOOKUP(H93,'Encoding Errors'!$A$2:$B$16,2,FALSE) -> Label occurs >90% of the time in training samples
A94: permanent pasture producing Sheep, ewe in United Kingdom. Additional description: High sugar and white clover pasture mix for sheep and cattle.. Additional Context: The functional unit for the permanent pasture producing sheep system in the United Kingdom is 1 kg of greasy wool. | B94: ML model predicted kg cold carcass weight/head but the humans predicted No kg cold carcass weight/head. | C94: 16.86747 | D94: 55 | E94: functionalUnitQA | F94: original | G94: rag | H94: 8.2 | I94: =VLOOKUP(H94,'Encoding Errors'!$A$2:$B$16,2,FALSE) -> In FU, AI model confuses cold carcass weight, cold dressed carcass weight, and liveweight | J94: Confused cold carcass weight with live weight
A95: permanent pasture producing Sheep, ewe in United Kingdom. Additional description: High sugar and white clover pasture mix for sheep and cattle.. Additional Context: The functional unit for the permanent pasture producing sheep system in the United Kingdom is 1 kg of greasy wool. | B95: ML model predicted kg cold carcass weight/head but the humans predicted No kg cold carcass weight/head. | C95: 16.86747 | D95: 58 | E95: functionalUnitQA | F95: original | G95: rag | H95: 8.1 | I95: =VLOOKUP(H95,'Encoding Errors'!$A$2:$B$16,2,FALSE) -> In FU, labeler only includes relative while AI model adds other categories
A96: permanent pasture producing Sheep, ewe in United Kingdom. Additional description: High sugar and white clover pasture mix for sheep and cattle.. Additional Context: The functional unit for the permanent pasture producing sheep system in the United Kingdom is 1 kg of greasy wool. | B96: ML model predicted kg liveweight/head but the humans predicted No kg liveweight/head. | C96: 54.457831 | D96: 58 | E96: functionalUnitQA | F96: original | G96: rag | H96: 8.1 | I96: =VLOOKUP(H96,'Encoding Errors'!$A$2:$B$16,2,FALSE) -> In FU, labeler only includes relative while AI model adds other categories
A97: permanent pasture producing Milk, cow, raw in United Kingdom. Additional description: based on a stocking density of two 650kg dairy cows per hectare and includes an allowance for followers. inventory is based on cows being housed for 250 days and outdoors for 115 days. | B97: ML model predicted No 1 ha but the humans predicted 1 ha. | C97: 4.6987952 | D97: 54 | E97: functionalUnitQA | F97: original | G97: no rag | H97: 1.2 | I97: =VLOOKUP(H97,'Encoding Errors'!$A$2:$B$16,2,FALSE) -> Label occurs <5% of the time in training samples
A98: permanent pasture producing Milk, cow, raw in United Kingdom. Additional description: based on a stocking density of two 650kg dairy cows per hectare and includes an allowance for followers. inventory is based on cows being housed for 250 days and outdoors for 115 days. | B98: ML model predicted % but the humans predicted No %. | C98: 11.084337 | D98: 54 | E98: functionalUnitQA | F98: original | G98: no rag | H98: 5 | I98: =VLOOKUP(H98,'Encoding Errors'!$A$2:$B$16,2,FALSE) -> AI model has justifiable response | J98: % is a common encoding for milk in HESTIA
A99: permanent pasture producing Milk, cow, raw in United Kingdom. Additional description: based on a stocking density of two 650kg dairy cows per hectare and includes an allowance for followers. inventory is based on cows being housed for 250 days and outdoors for 115 days. | B99: ML model predicted relative but the humans predicted No relative. | C99: 95.301205 | D99: 54 | E99: functionalUnitQA | F99: original | G99: no rag | H99: 1.4 | I99: =VLOOKUP(H99,'Encoding Errors'!$A$2:$B$16,2,FALSE) -> Label occurs >90% of the time in training samples
A100: permanent pasture producing Sheep, ewe in United Kingdom. Additional description: High sugar and white clover pasture mix for sheep and cattle.. | B100: ML model predicted kg liveweight/head but the humans predicted No kg liveweight/head. | C100: 54.457831 | D100: 58 | E100: functionalUnitQA | F100: original | G100: no rag | H100: 8.1 | I100: =VLOOKUP(H100,'Encoding Errors'!$A$2:$B$16,2,FALSE) -> In FU, labeler only includes relative while AI model adds other categories
A101: permanent pasture producing Hides, dairy cattle, fresh in United Kingdom. Additional description: based on a stocking density of two 650kg dairy cows per hectare and includes an allowance for followers. inventory is based on cows being housed for 250 days and outdoors for 115 days. Additional Context: The product being assessed is 1 L of packaged fluid milk. | B101: ML model predicted Meat but the humans predicted No Meat. | C101: 13.614458 | D101: 79 | E101: productQA | F101: original | G101: rag | H101: 4 | I101: =VLOOKUP(H101,'Encoding Errors'!$A$2:$B$16,2,FALSE) -> AI model likely incorrect
A102: permanent pasture producing Hides, dairy cattle, fresh in United Kingdom. Additional description: based on a stocking density of two 650kg dairy cows per hectare and includes an allowance for followers. inventory is based on cows being housed for 250 days and outdoors for 115 days. | B102: ML model predicted Meat but the humans predicted No Meat. | C102: 13.614458 | D102: 79 | E102: productQA | F102: original | G102: no rag | H102: 4 | I102: =VLOOKUP(H102,'Encoding Errors'!$A$2:$B$16,2,FALSE) -> AI model likely incorrect
A103: animal housing producing Layer chicken, pullet in Mexico. Additional description: Chick breeding (6 weeks). Additional Context: For the animal housing producing Layer chicken production system, the appropriate allocation method is "none required" because system expansion is not necessary. | B103: ML model predicted none required but the humans predicted No none required. | C103: 13.975904 | D103: 41 | E103: allocationQA | F103: original | G103: rag | H103: 7 | I103: =VLOOKUP(H103,'Encoding Errors'!$A$2:$B$16,2,FALSE) -> RAG Added Misinformation | J103: RAG said that the method was none and none required, but the answer was only none
A104: animal housing producing Layer chicken, pullet in Mexico. Additional description: Chick breeding (6 weeks). | B104: ML model predicted none required but the humans predicted No none required. | C104: 13.975904 | D104: 41 | E104: allocationQA | F104: original | G104: no rag | H104: 2.1 | I104: =VLOOKUP(H104,'Encoding Errors'!$A$2:$B$16,2,FALSE) -> In Allocation, confused none with none required | J104: Difference between none and none required
A105: permanent pasture producing Beef cattle in Brazil. Additional description: Rerfence system where feeding is performed only by grazing anfd the supply of mineral supplementation.. | B105: ML model predicted No none required but the humans predicted none required. | C105: 13.975904 | D105: 48 | E105: allocationQA | F105: original | G105: no rag | H105: 2.1 | I105: =VLOOKUP(H105,'Encoding Errors'!$A$2:$B$16,2,FALSE) -> In Allocation, confused none with none required | J105: Difference between none and none required
A106: permanent pasture producing Beef cattle in Brazil. Additional description: Rerfence system where feeding is performed only by grazing anfd the supply of mineral supplementation.. Additional Context: For the permanent pasture producing Beef cattle in Brazil production system, the appropriate allocation method is biophysical. This is because the system is complex, multi-output, and socio-ecological, and system expansion may not be feasible or desirable due to the lack of comparable substitutes for the co-products. Biophysical allocation is a suitable method for this system as it takes into account the physical relationships between the products, such as mass, volume, or carbon content. | B106: ML model predicted No none required but the humans predicted none required. | C106: 13.975904 | D106: 48 | E106: allocationQA | F106: original | G106: rag | H106: 7 | I106: =VLOOKUP(H106,'Encoding Errors'!$A$2:$B$16,2,FALSE) -> RAG Added Misinformation | J106: RAG said biophysical when the answer was none required
A107: animal housing producing Pig in Denmark. Additional description: Piglets. | B107: ML model predicted No none required but the humans predicted none required. | C107: 13.975904 | D107: 60 | E107: allocationQA | F107: original | G107: no rag | H107: 2.2 | I107: =VLOOKUP(H107,'Encoding Errors'!$A$2:$B$16,2,FALSE) -> In Allocation, chose economic when the humans chose a more specific label | J107: Model wants economic allocation when humans want none for pig production
A108: animal housing producing Layer chicken, pullet in Mexico. Additional description: Bird development phase (10 weeks). | B108: ML model predicted none required but the humans predicted No none required. | C108: 13.975904 | D108: 84 | E108: allocationQA | F108: original | G108: no rag | H108: 2.1 | I108: =VLOOKUP(H108,'Encoding Errors'!$A$2:$B$16,2,FALSE) -> In Allocation, confused none with none required | J108: Difference between none and none required
A109: animal housing producing Pig in Netherlands. Additional description: Sow and piglets. | B109: ML model predicted No none required but the humans predicted none required. | C109: 13.975904 | D109: 95 | E109: allocationQA | F109: original | G109: no rag | H109: 2.2 | I109: =VLOOKUP(H109,'Encoding Errors'!$A$2:$B$16,2,FALSE) -> In Allocation, chose economic when the humans chose a more specific label | J109: Model wants economic allocation when humans want none for pig production
A110: agri-food processor producing Meat, chicken (cold carcass weight) in Thailand. Additional description: Frozen processing factory. | B110: ML model predicted No none required but the humans predicted none required. | C110: 13.975904 | D110: 100 | E110: allocationQA | F110: original | G110: no rag | H110: 2.2 | I110: =VLOOKUP(H110,'Encoding Errors'!$A$2:$B$16,2,FALSE) -> In Allocation, chose economic when the humans chose a more specific label | J110: Model wants economic allocation when humans want none for chicken production
A111: animal housing producing Layer chicken, pullet in Mexico. Additional description: Bird development phase (10 weeks). Additional Context: Based on the provided information, since the production system is a complex, multi-output, socio-ecological system, and system expansion may not be feasible or desirable, the appropriate allocation method is "none required". | B111: ML model predicted none required but the humans predicted No none required. | C111: 13.975904 | D111: 84 | E111: allocationQA | F111: original | G111: rag | H111: 2.1 | I111: =VLOOKUP(H111,'Encoding Errors'!$A$2:$B$16,2,FALSE) -> In Allocation, confused none with none required
A112: animal housing producing Pig in Netherlands. Additional description: Sow and piglets. Additional Context: For the animal housing production system producing pigs in the Netherlands, the appropriate allocation method is "none required" because system expansion is not necessary. | B112: ML model predicted No none required but the humans predicted none required. | C112: 13.975904 | D112: 95 | E112: allocationQA | F112: original | G112: rag | H112: 2.2 | I112: =VLOOKUP(H112,'Encoding Errors'!$A$2:$B$16,2,FALSE) -> In Allocation, chose economic when the humans chose a more specific label
A113: animal housing producing Pig in Denmark. Additional description: Piglets. | B113: ML model predicted No days but the humans predicted days. | C113: 10 | D113: 60 | E113: functionalUnitQA | F113: original | G113: no rag | H113: 5 | I113: =VLOOKUP(H113,'Encoding Errors'!$A$2:$B$16,2,FALSE) -> AI model has justifiable response | J113: Unclear why days is included as a label
A114: agri-food processor producing Meat, beef cattle (cold carcass weight) in Ireland. | B114: ML model predicted % but the humans predicted No %. | C114: 11.084337 | D114: 63 | E114: functionalUnitQA | F114: original | G114: no rag | H114: 4 | I114: =VLOOKUP(H114,'Encoding Errors'!$A$2:$B$16,2,FALSE) -> AI model likely incorrect | J114: FU is contained in product description
A115: permanent pasture producing Sheep, ewe in United Kingdom. Additional description: Generic grass pasture for sheep and cattle.. | B115: ML model predicted No kg cold carcass weight/head but the humans predicted kg cold carcass weight/head. | C115: 16.86747 | D115: 66 | E115: functionalUnitQA | F115: original | G115: no rag | H115: 8.2 | I115: =VLOOKUP(H115,'Encoding Errors'!$A$2:$B$16,2,FALSE) -> In FU, AI model confuses cold carcass weight, cold dressed carcass weight, and liveweight
A116: animal housing producing Pig in Denmark. Additional description: Piglets. Additional Context: The functional unit for the animal housing producing Pig in Denmark is 1 kg of live weight (LW) of pigs leaving the pig unit, including culled SOWS and slaughter pigs. | B116: ML model predicted No days but the humans predicted days. | C116: 10 | D116: 60 | E116: functionalUnitQA | F116: original | G116: rag | H116: 5 | I116: =VLOOKUP(H116,'Encoding Errors'!$A$2:$B$16,2,FALSE) -> AI model has justifiable response | J116: Unclear why labeler included days
A117: agri-food processor producing Meat, beef cattle (cold carcass weight) in Ireland. Additional Context: The functional unit for the agri-food processor producing Meat, beef cattle (cold carcass weight) in Ireland is 1 kg of live weight (LW) of beef cattle. | B117: ML model predicted % but the humans predicted No %. | C117: 11.084337 | D117: 63 | E117: functionalUnitQA | F117: original | G117: rag | H117: 4 | I117: =VLOOKUP(H117,'Encoding Errors'!$A$2:$B$16,2,FALSE) -> AI model likely incorrect | J117: % seems very wrong for meat production
A118: permanent pasture producing Sheep, ewe in United Kingdom. Additional description: Generic grass pasture for sheep and cattle.. Additional Context: The functional unit for the production system of permanent pasture producing sheep in the United Kingdom is one animal. | B118: ML model predicted No kg cold carcass weight/head but the humans predicted kg cold carcass weight/head. | C118: 16.86747 | D118: 66 | E118: functionalUnitQA | F118: original | G118: rag | H118: 8.2 | I118: =VLOOKUP(H118,'Encoding Errors'!$A$2:$B$16,2,FALSE) -> In FU, AI model confuses cold carcass weight, cold dressed carcass weight, and liveweight
A119: producing Broiler chicken in Russia. Additional description: Poultry production under the conditions of the central region in european Russia. Additional Context: The functional unit for the production system of producing Broiler chicken in Russia is 1 kg of live weight of broiler chicken. | B119: ML model predicted days but the humans predicted No days. | C119: 10 | D119: 68 | E119: functionalUnitQA | F119: original | G119: rag | H119: 4 | I119: =VLOOKUP(H119,'Encoding Errors'!$A$2:$B$16,2,FALSE) -> AI model likely incorrect
A120: producing Broiler chicken in Russia. Additional description: Poultry production under the conditions of the central region in european Russia. Additional Context: The functional unit for the production system of producing Broiler chicken in Russia is 1 kg of live weight of broiler chicken. | B120: ML model predicted No % but the humans predicted %. | C120: 11.084337 | D120: 68 | E120: functionalUnitQA | F120: original | G120: rag | H120: 4 | I120: =VLOOKUP(H120,'Encoding Errors'!$A$2:$B$16,2,FALSE) -> AI model likely incorrect
A121: permanent pasture producing Milk, cow, raw (FPCM) in Ireland. Additional description: A representative sample of Irish dairy farms.. Additional Context: The functional unit for the production system is 1 kg FPCM (Fat and Protein Corrected Milk). | B121: ML model predicted % but the humans predicted No %. | C121: 11.084337 | D121: 73 | E121: functionalUnitQA | F121: original | G121: rag | H121: 5 | I121: =VLOOKUP(H121,'Encoding Errors'!$A$2:$B$16,2,FALSE) -> AI model has justifiable response | J121: % is a common encoding for milk in HESTIA
A122: producing Broiler chicken in Russia. Additional description: Poultry production under the conditions of the central region in european Russia. | B122: ML model predicted days but the humans predicted No days. | C122: 10 | D122: 68 | E122: functionalUnitQA | F122: original | G122: no rag | H122: 5 | I122: =VLOOKUP(H122,'Encoding Errors'!$A$2:$B$16,2,FALSE) -> AI model has justifiable response | J122: Unclear why days and % are switched
A123: animal housing producing Beef cattle, calf (female, weaned) in United Kingdom. Additional description: Indoor cattle system.. Additional Context: The functional unit for the animal housing producing Beef cattle, calf (female, weaned) in the United Kingdom is 1 kg of live weight (LW) of beef cattle. | B123: ML model predicted kg liveweight/head but the humans predicted No kg liveweight/head. | C123: 56.815287 | D123: 31 | E123: functionalUnitQA | F123: recalculated | G123: rag | H123: 8.1 | I123: =VLOOKUP(H123,'Encoding Errors'!$A$2:$B$16,2,FALSE) -> In FU, labeler only includes relative while AI model adds other categories
A124: permanent pasture producing Sheep, ewe in United Kingdom. Additional description: High sugar pasture for sheep and cattle.. Additional Context: The functional unit for the production system of permanent pasture producing sheep in the United Kingdom is 1 ewe. | B124: ML model predicted No kg cold carcass weight/head but the humans predicted kg cold carcass weight/head. | C124: 18.216561 | D124: 35 | E124: functionalUnitQA | F124: recalculated | G124: rag | H124: 8.2 | I124: =VLOOKUP(H124,'Encoding Errors'!$A$2:$B$16,2,FALSE) -> In FU, AI model confuses cold carcass weight, cold dressed carcass weight, and liveweight
A125: permanent pasture producing Sheep, lamb in United Kingdom. Additional description: High sugar and white clover pasture mix for sheep and cattle.. Additional Context: The functional unit for the permanent pasture producing sheep and lamb system in the United Kingdom is 1 animal (sheep). | B125: ML model predicted kg liveweight/head but the humans predicted No kg liveweight/head. | C125: 56.815287 | D125: 36 | E125: functionalUnitQA | F125: recalculated | G125: rag | H125: 8.1 | I125: =VLOOKUP(H125,'Encoding Errors'!$A$2:$B$16,2,FALSE) -> In FU, labeler only includes relative while AI model adds other categories
A126: permanent pasture producing Dairy cattle, heifer in New Zealand. Additional description: Off-site replacement cow pasture grazing from weaned calf -> 90% of mature weight (2mo -> 22mo) (2017/18). Additional Context: The functional unit for the production system is 1 mature dairy cow. | B126: ML model predicted No days but the humans predicted days. | C126: 10.191083 | D126: 38 | E126: functionalUnitQA | F126: recalculated | G126: rag | H126: 5 | I126: =VLOOKUP(H126,'Encoding Errors'!$A$2:$B$16,2,FALSE) -> AI model has justifiable response | J126: Unclear why the study has the FU it does
A127: permanent pasture producing Dairy cattle, heifer in New Zealand. Additional description: Off-site replacement cow pasture grazing from weaned calf -> 90% of mature weight (2mo -> 22mo) (2017/18). Additional Context: The functional unit for the production system is 1 mature dairy cow. | B127: ML model predicted No kg liveweight/head but the humans predicted kg liveweight/head. | C127: 56.815287 | D127: 38 | E127: functionalUnitQA | F127: recalculated | G127: rag | H127: 5 | I127: =VLOOKUP(H127,'Encoding Errors'!$A$2:$B$16,2,FALSE) -> AI model has justifiable response | J127: Unclear why the study has the FU it does
A128: permanent pasture producing Beef cattle, heifer in United Kingdom. Additional description: High sugar pasture for sheep and cattle.. Additional Context: The functional unit for the permanent pasture producing Beef cattle, heifer in the United Kingdom is 1 kg of live weight (LW) of beef cattle. | B128: ML model predicted kg cold carcass weight/head but the humans predicted No kg cold carcass weight/head. | C128: 18.216561 | D128: 39 | E128: functionalUnitQA | F128: recalculated | G128: rag | H128: 8.2 | I128: =VLOOKUP(H128,'Encoding Errors'!$A$2:$B$16,2,FALSE) -> In FU, AI model confuses cold carcass weight, cold dressed carcass weight, and liveweight
A129: permanent pasture producing Sheep, ewe in United Kingdom. Additional description: Generic grass pasture for sheep and cattle.. Additional Context: The functional unit for the production system of permanent pasture producing sheep in the United Kingdom is one animal. | B129: ML model predicted kg cold carcass weight/head but the humans predicted No kg cold carcass weight/head. | C129: 18.216561 | D129: 40 | E129: functionalUnitQA | F129: recalculated | G129: rag | H129: 8.2 | I129: =VLOOKUP(H129,'Encoding Errors'!$A$2:$B$16,2,FALSE) -> In FU, AI model confuses cold carcass weight, cold dressed carcass weight, and liveweight
A130: permanent pasture producing Sheep, ewe in United Kingdom. Additional description: Generic grass pasture for sheep and cattle.. Additional Context: The functional unit for the production system of permanent pasture producing sheep in the United Kingdom is one animal. | B130: ML model predicted kg cold carcass weight/head but the humans predicted No kg cold carcass weight/head. | C130: 18.216561 | D130: 41 | E130: functionalUnitQA | F130: recalculated | G130: rag | H130: 8.1 | I130: =VLOOKUP(H130,'Encoding Errors'!$A$2:$B$16,2,FALSE) -> In FU, labeler only includes relative while AI model adds other categories
A131: permanent pasture producing Sheep, ewe in United Kingdom. Additional description: High sugar pasture for sheep and cattle.. | B131: ML model predicted No kg cold carcass weight/head but the humans predicted kg cold carcass weight/head. | C131: 18.216561 | D131: 35 | E131: functionalUnitQA | F131: recalculated | G131: no rag | H131: 8.2 | I131: =VLOOKUP(H131,'Encoding Errors'!$A$2:$B$16,2,FALSE) -> In FU, AI model confuses cold carcass weight, cold dressed carcass weight, and liveweight
A132: permanent pasture producing Sheep, lamb in United Kingdom. Additional description: High sugar and white clover pasture mix for sheep and cattle.. | B132: ML model predicted kg liveweight/head but the humans predicted No kg liveweight/head. | C132: 56.815287 | D132: 36 | E132: functionalUnitQA | F132: recalculated | G132: no rag | H132: 8.1 | I132: =VLOOKUP(H132,'Encoding Errors'!$A$2:$B$16,2,FALSE) -> In FU, labeler only includes relative while AI model adds other categories
A133: permanent pasture producing Beef cattle, calf (female, weaned) in United Kingdom. Additional description: Generic grass pasture for sheep and cattle.. What is in the system boundary? | B133: ML model predicted True_freshForage but the humans predicted No True_freshForage. | C133: 87.388535 | D133: 3 | E133: systemBoundaryQA | F133: recalculated | G133: no rag | H133: 3.1 | I133: =VLOOKUP(H133,'Encoding Errors'!$A$2:$B$16,2,FALSE) -> In the system boundary, the authors of the study did not report an item the AI model wants to consider for completeness
A134: permanent pasture producing Beef cattle, calf (female, weaned) in United Kingdom. Additional description: Generic grass pasture for sheep and cattle.. What is in the system boundary? Additional Context: The system boundary of the production system includes:- Livestock (cattle, bulls, heifers, calves, and dry cows)- Local feeds (alfalfa and maize)- Fertilizers- Irrigation- Pesticides- Machinery (roads, irrigation infrastructure, buildings, and tools)- Fuels (diesel and electricity)- Water for livestock- Manure management- Pasture production- Crop production- Animal transport- Calf production- Fattening- Breeding- Feed production- Manure- Pasture recovery- Grazing- Supplements (mineral salts)- Farm infrastructure (corral, administration building, workers' housing)- Farm operations (fertilizer application, manure application, forage production)- Farm management (farm decisions, including animal selection, feeding, and breeding)- Farm endowments (prices, farm resources)- Farm activities (cash crop and dairy production)- Farm operations (livestock management, feed planning, and animal health)- Farm infrastructure (access road, ponds, creek)- Farm management practices (animal breeding, reproduction, and slaughter)- Farm operations (animal transport, slaughter, and processing)- Farm | B134: ML model predicted True_freshForage but the humans predicted No True_freshForage. | C134: 87.388535 | D134: 3 | E134: systemBoundaryQA | F134: recalculated | G134: rag | H134: 3.1 | I134: =VLOOKUP(H134,'Encoding Errors'!$A$2:$B$16,2,FALSE) -> In the system boundary, the authors of the study did not report an item the AI model wants to consider for completeness
A135: permanent pasture producing Beef cattle, cow in Brazil. Additional description: Beef, fertilized Guinea grass (Panicum maximum cv. TanzÃ¢nia) pasture + 75-day finishing period in confinement (Scenario 5). What is in the system boundary? | B135: ML model predicted No True_water but the humans predicted True_water. | C135: 24.337349 | D135: 23 | E135: systemBoundaryQA | F135: original | G135: no rag | H135: 3.2 | I135: =VLOOKUP(H135,'Encoding Errors'!$A$2:$B$16,2,FALSE) -> In the system boundary, the AI model does not want to report an item the authors of the study did report for completeness
...

Sheet Encoding Errors
A1: Table of Rationale | O1: Notes:
A2: 1.1 | B2: Label not in training data | O2: Frequency of label occurences precedes other label choices
A3: 1.2 | B3: Label occurs <5% of the time in training samples | O3: System boundary had a lot of trouble with fresh forage
A4: 1.3 | B4: Label occurs <10% of the time in training samples | O4: The reviewer noticed that classifying errors in FU was difficult with the given sentence description of the system was quite difficult.
A5: 1.4 | B5: Label occurs >90% of the time in training samples | O5: Sometimes the labeler would put the FU in the product description and not the FU labels
A6: 2.1 | B6: In Allocation, confused none with none required
A7: 2.2 | B7: In Allocation, chose economic when the humans chose a more specific label
A8: 3.1 | B8: In the system boundary, the authors of the study did not report an item the AI model wants to consider for completeness
A9: 3.2 | B9: In the system boundary, the AI model does not want to report an item the authors of the study did report for completeness
A10: 4 | B10: AI model likely incorrect
A11: 5 | B11: AI model has justifiable response
A12: 6 | B12: Unclear
A13: 7 | B13: RAG Added Misinformation
A14: 8.1 | B14: In FU, labeler only includes relative while AI model adds other categories
A15: 8.2 | B15: In FU, AI model confuses cold carcass weight, cold dressed carcass weight, and liveweight
A16: 9 | B16: Human authors/labelers appear to have made a mistake
